Metadata-Version: 2.1
Name: django-navbar-client
Version: 1.0.3
Summary: Easy remote oauth identification
Home-page: https://github.com/josubg/django_navbar_client
Author: Josu Bermudez
Author-email: josu.bermudez@deusto.es
License: UNKNOWN
Project-URL: Bug Reports, https://github.com/josubg/django_navbar_client/issues
Project-URL: Source, https://github.com/josubg/django_navbar_client
Keywords: Fiware Orion development
Platform: UNKNOWN
Classifier: Development Status :: 4 - Beta
Classifier: Intended Audience :: Developers
Classifier: Topic :: Software Development :: Libraries
Classifier: Topic :: Software Development :: Libraries :: Python Modules
Classifier: License :: OSI Approved :: GNU General Public License v3 (GPLv3)
Classifier: Programming Language :: Python :: 3
Classifier: Programming Language :: Python :: 3.4
Classifier: Programming Language :: Python :: 3.5
Classifier: Programming Language :: Python :: 3.6
Classifier: Framework :: Django :: 2.0
Requires-Dist: django
Requires-Dist: requests
